douyindl/DOWNLOADER.py
douyindl/__init__.py
douyindl-6.0.9.dist-info/METADATA
douyindl-6.0.9.dist-info/WHEEL
douyindl-6.0.9.dist-info/top_level.txt
douyindl-6.0.9.dist-info/RECORD
